merkle_patricia_trie-0.4.0.dist-info/licenses/LICENSE
mpt/__init__.py
mpt/hash.py
mpt/mpt.py
mpt/nibble_path.py
mpt/node.py
merkle_patricia_trie-0.4.0.dist-info/METADATA
merkle_patricia_trie-0.4.0.dist-info/WHEEL
merkle_patricia_trie-0.4.0.dist-info/top_level.txt
merkle_patricia_trie-0.4.0.dist-info/RECORD
