Metadata-Version: 2.4
Name: merkle-patricia-trie
Version: 0.4.0
Summary: A simlpe Merkle Patricia Trie implementation
Author-email: sterliakov <terlya.stas@gmail.com>
License: Copyright (c) 2019 Igor Aleksanov
Project-URL: Home, https://github.com/sterliakov/merkle-patricia-trie
Project-URL: Issues, https://github.com/sterliakov/merkle-patricia-trie/issues
Project-URL: Source, https://github.com/sterliakov/merkle-patricia-trie
Keywords: trie,data-structures,datastructures,merkle-patricia-trie,blockchain,ethereum
Classifier: Programming Language :: Python :: 3
Classifier: Intended Audience :: Developers
Classifier: License :: OSI Approved :: MIT License
Classifier: Operating System :: OS Independent
Classifier: Topic :: Security :: Cryptography
Requires-Python: >=3.9
License-File: LICENSE
Requires-Dist: pycryptodome<4,>=3.22.0
Requires-Dist: rlp<5.0,>=2.0
Dynamic: license-file
